LICENSE
pyflowdroid/__init__.py
pyflowdroid/__main__.py
pyflowdroid/_cli_tools.py
pyflowdroid/analyze.py
pyflowdroid/consts.py
pyflowdroid/download.py
pyflowdroid/install.py
pyflowdroid/sources_sinks/large.txt
pyflowdroid/sources_sinks/small.txt
pyflowdroid-0.2.0.dist-info/LICENSE
pyflowdroid-0.2.0.dist-info/WHEEL
pyflowdroid-0.2.0.dist-info/METADATA
pyflowdroid-0.2.0.dist-info/RECORD
