Metadata-Version: 2.1
Name: pyflowdroid
Version: 0.2.0
Summary: Python wrapper to use FlowDroid APK analyzer.
Home-page: https://github.com/gvieralopez/pyFlowDroid
License: MIT
Keywords: apk,flow analyisis,android
Author: Gustavo Viera López
Author-email: gvieralopez@gmail.com
Requires-Python: >=3.7,<4.0
Classifier: License :: OSI Approved :: MIT License
Classifier: Programming Language :: Python :: 3
Classifier: Programming Language :: Python :: 3.10
Classifier: Programming Language :: Python :: 3.7
Classifier: Programming Language :: Python :: 3.8
Classifier: Programming Language :: Python :: 3.9
Requires-Dist: beautifulsoup4 (>=4.11.1,<5.0.0)
Requires-Dist: lxml (>=4.8.0,<5.0.0)
Requires-Dist: progressbar (>=2.5,<3.0)
Requires-Dist: typer (>=0.4.1,<0.5.0)
Project-URL: Repository, https://github.com/gvieralopez/pyFlowDroid
